tpds/__init__.py
tpds/proto_boards/__init__.py
tpds/proto_boards/boards.yaml
tpds/proto_boards/ATSAME54-XPRO/ATSAME54-XPRO.hex
tpds/proto_boards/ATSAME54-XPRO/ATSAME54-XPRO.png
tpds/proto_boards/ATSAME54-XPRO/Factory_Program.X/Makefile
tpds/proto_boards/ATSAME54-XPRO/Factory_Program.X/nbproject/Makefile-def.mk
tpds/proto_boards/ATSAME54-XPRO/Factory_Program.X/nbproject/Makefile-genesis.properties
tpds/proto_boards/ATSAME54-XPRO/Factory_Program.X/nbproject/Makefile-impl.mk
tpds/proto_boards/ATSAME54-XPRO/Factory_Program.X/nbproject/Makefile-local-def.mk
tpds/proto_boards/ATSAME54-XPRO/Factory_Program.X/nbproject/Makefile-variables.mk
tpds/proto_boards/ATSAME54-XPRO/Factory_Program.X/nbproject/configurations.xml
tpds/proto_boards/ATSAME54-XPRO/Factory_Program.X/nbproject/def.production
tpds/proto_boards/ATSAME54-XPRO/Factory_Program.X/nbproject/project.properties
tpds/proto_boards/ATSAME54-XPRO/Factory_Program.X/nbproject/project.xml
tpds/proto_boards/ATSAME54-XPRO/Factory_Program.X/nbproject/private/configurations.xml
tpds/proto_boards/ATSAME54-XPRO/Factory_Program.X/nbproject/private/private.xml
tpds/proto_boards/DM320109/DM320109.hex
tpds/proto_boards/DM320118/DM320118.hex
tpds/proto_boards/DM320118/DM320118.png
tpds/proto_boards/DM320118/DM320118_WINC.png
tpds/proto_boards/DM320118/Factory_Program.X/Makefile
tpds/proto_boards/DM320118/Factory_Program.X/nbproject/Makefile-genesis.properties
tpds/proto_boards/DM320118/Factory_Program.X/nbproject/configurations.xml
tpds/proto_boards/DM320118/Factory_Program.X/nbproject/project.xml
tpds/proto_boards/DM320118/Factory_Program.X/nbproject/private/configurations.xml
tpds/proto_boards/DM320118/Factory_Program.X/nbproject/private/private.xml
tpds/proto_boards/DM320118/winc_firmware_upgrade/README.md
tpds/proto_boards/DM320118/winc_firmware_upgrade/nedbg_fw-1.18.528.zip
tpds/proto_boards/DM320118/winc_firmware_upgrade/winc_RootCerts_update.bat
tpds/proto_boards/DM320118/winc_firmware_upgrade/winc_firmware_update.bat
tpds_boards-2.2.13.dist-info/licenses/LICENSE
tpds_boards-2.2.13.dist-info/METADATA
tpds_boards-2.2.13.dist-info/WHEEL
tpds_boards-2.2.13.dist-info/top_level.txt
tpds_boards-2.2.13.dist-info/RECORD
